sqlrepo-5.5.1.dist-info/METADATA
sqlrepo-5.5.1.dist-info/WHEEL
sqlrepo-5.5.1.dist-info/entry_points.txt
sqlrepo/.pytest_cache/.gitignore
sqlrepo/.pytest_cache/CACHEDIR.TAG
sqlrepo/.pytest_cache/README.md
sqlrepo/.pytest_cache/v/cache/nodeids
sqlrepo/.pytest_cache/v/cache/stepwise
sqlrepo/__init__.py
sqlrepo/abc.py
sqlrepo/config.py
sqlrepo/constants.py
sqlrepo/exc.py
sqlrepo/ext/__init__.py
sqlrepo/ext/fastapi/__init__.py
sqlrepo/ext/fastapi/containers.py
sqlrepo/ext/fastapi/helpers.py
sqlrepo/ext/fastapi/pagination.py
sqlrepo/ext/fastapi/services.py
sqlrepo/ext/fastapi/stubs.py
sqlrepo/logger.py
sqlrepo/py.typed
sqlrepo/queries.py
sqlrepo/repositories.py
sqlrepo/types.py
sqlrepo/wrappers.py
sqlrepo-5.5.1.dist-info/RECORD
