Metadata-Version: 2.1
Name: sqlrepo
Version: 5.5.1
Summary: sqlalchemy repositories with crud operations and other utils for it.
Author-Email: Dmitriy Lunev <dima.lunev14@gmail.com>
License: MIT
Requires-Python: >=3.11
Requires-Dist: sqlalchemy>=2.0
Requires-Dist: python-dev-utils>=7.0.1
Requires-Dist: sqlalchemy-dev-utils>=1.3.0
Requires-Dist: sqlalchemy-filter-converter>=1.4.0
Provides-Extra: fastapi
Requires-Dist: fastapi>=0.100; extra == "fastapi"
Requires-Dist: verbose_http_exceptions>=1.1.1; extra == "fastapi"
